Metadata-Version: 1.1
Name: ardianmaliqaj
Version: 20210208140341338400
Summary: building first pip
Home-page: UNKNOWN
Author: Ardian Maliqaj
Author-email: ardianmaliqaj0@gmail.com
License: MIT
Keywords: pip installable module
Platform: UNKNOWN
Classifier: Development Status :: 5 - Production/Stable
Classifier: Intended Audience :: Education
Classifier: Operating System :: Microsoft :: Windows :: Windows 10
Classifier: License :: OSI Approved :: MIT License
Classifier: Programming Language :: Python :: 3
